ioctl_hunter/__init__.py
ioctl_hunter/core.py
ioctl_hunter/frida/__init__.py
ioctl_hunter/frida/script.ts
ioctl_hunter/lib/__init__.py
ioctl_hunter/lib/hooking.py
ioctl_hunter/lib/results.py
ioctl_hunter/lib/state.py
ioctl_hunter/ui/__init__.py
ioctl_hunter/ui/console.py
ioctl_hunter/ui/display.py
ioctl_hunter/ui/keys_reader.py
ioctl_hunter/ui/main.py
ioctl_hunter/ui/options.py
ioctl_hunter/utils/__init__.py
ioctl_hunter/utils/logger.py
ioctl_hunter/utils/misc.py
IoctlHunter-0.2.dist-info/LICENSE
IoctlHunter-0.2.dist-info/METADATA
IoctlHunter-0.2.dist-info/WHEEL
IoctlHunter-0.2.dist-info/entry_points.txt
IoctlHunter-0.2.dist-info/top_level.txt
IoctlHunter-0.2.dist-info/RECORD
