Metadata-Version: 2.1
Name: IoctlHunter
Version: 0.2
Summary: CLI tools allowing to ease the dynamic analysis of IOCTL calls in destination to Windows drivers for RedTeam/pentest perspectives
Author: Zak
License: MIT
Requires-Python: >=3.6
License-File: LICENSE
Requires-Dist: colorama
Requires-Dist: frida-tools
Requires-Dist: psutil
